asncounter.py
asncounter-0.5.0.dist-info/licenses/LICENSE
asncounter-0.5.0.dist-info/METADATA
asncounter-0.5.0.dist-info/WHEEL
asncounter-0.5.0.dist-info/entry_points.txt
asncounter-0.5.0.dist-info/top_level.txt
asncounter-0.5.0.dist-info/RECORD
