Metadata-Version: 2.4
Name: asncounter
Version: 0.5.0
Summary: Count the number of hits (HTTP, packets, etc) per autonomous system number (ASN) and related network blocks
Author-email: Antoine Beaupré <anarcat@debian.org>
License-Expression: AGPL-3.0-or-later
Project-URL: Homepage, https://gitlab.com/anarcat/asncounter
Project-URL: Issues, https://gitlab.com/anarcat/asncounter/issues
Classifier: Environment :: Console
Classifier: Programming Language :: Python :: 3
Classifier: Operating System :: POSIX :: Linux
Requires-Python: >=3.10
License-File: LICENSE
Requires-Dist: pyasn
Provides-Extra: full
Requires-Dist: manhole; extra == "full"
Requires-Dist: netaddr; extra == "full"
Requires-Dist: scapy; extra == "full"
Requires-Dist: prometheus_client; extra == "full"
Provides-Extra: test
Requires-Dist: pytest; extra == "test"
Requires-Dist: pytest-cov; extra == "test"
Dynamic: license-file
